huparry/__init__.py
huparry/aiosqlite.py
huparry/atcoder.py
huparry/codeforces.py
huparry/config.py
huparry/nowcoder.py
huparry/utils.py
huparry-0.0.1.dist-info/LICENSE
huparry-0.0.1.dist-info/METADATA
huparry-0.0.1.dist-info/WHEEL
huparry-0.0.1.dist-info/RECORD
