Metadata-Version: 2.1
Name: huparry
Version: 0.0.1
Summary: huparry库，日后将嵌入一些有用的功能
Home-page: https://github.com/HuParry/huparry
License: MIT
Author: HuParry
Author-email: hu_parry@qq.com
Requires-Python: >=3.8
Classifier: License :: OSI Approved :: MIT License
Classifier: Programming Language :: Python :: 3
Classifier: Programming Language :: Python :: 3.8
Classifier: Programming Language :: Python :: 3.9
Classifier: Programming Language :: Python :: 3.10
Classifier: Programming Language :: Python :: 3.11
Classifier: Programming Language :: Python :: 3.12
Classifier: Programming Language :: Python :: 3.13
Requires-Dist: aiosqlite (>=0.13.0,<0.14.0)
Requires-Dist: bs4 (>=0.0.1)
Requires-Dist: fake-useragent (>=1.1.3)
Requires-Dist: httpx (>=0.20.0,<1.0.0)
Requires-Dist: nonebot-adapter-onebot (>=2.1.5)
Requires-Dist: nonebot2[fastapi] (>=2.0.0,<3.0.0)
Project-URL: Repository, https://github.com/HuParry/huparry
